[
  {
    "titulo": " Dom Quixote",
    "autor": "Miguel de Cervantes",
    "paginas": "1605",
    "preço": "R$9,95"
  },

  {
    "titulo": "Guerra e Paz",
    "autor": "Liev Tolstói",
    "paginas": "1869",
    "preço": "R$71,90"

  },


  {
    "titulo": "A Montanha Mágica",
    "autor": "Thomas Mann",
    "paginas": "1924",
    "preço": "R$56,94"
  },


  {
    "titulo": "Cem Anos de Solidão",
    "autor": "Gabriel García Márquez",
    "paginas": "1967",
    "preço": "R$33,28"

  },

  {
    "titulo": "Ulisses",
    "autor": "James Joyce",
    "paginas": "1922",
    "preço": "R$47,05"
  },

  {
    "titulo": "Em Busca do Tempo Perdido",
    "autor": " Marcel Proust",
    "paginas": "1913",
    "preço": "R$ 42,90"
  },

  {
    "titulo": "A Divina Comédia",
    "autor": "Dante Alighieri",
    "paginas": "1321",
    "preço": "R$ 66,74"
  }

]